minidb_project/__init__.py
minidb_project/mini_db.py
minidb_project-0.7.dist-info/METADATA
minidb_project-0.7.dist-info/WHEEL
minidb_project-0.7.dist-info/top_level.txt
minidb_project-0.7.dist-info/RECORD
