Metadata-Version: 2.1
Name: minidb-project
Version: 0.7
Summary: Uma biblioteca de banco de dados simples que funciona a partir do script
Home-page: https://grupomuller.org.br
Author: Arthur Saert
Author-email: contato@grupomuller.org.br
Classifier: Programming Language :: Python :: 3
Classifier: License :: OSI Approved :: MIT License
Classifier: Operating System :: OS Independent
Requires-Python: >=3.6
